SSG_API_test/SSG_API_test.py
SSG_API_test-0.0.3.dist-info/LICENSE
SSG_API_test-0.0.3.dist-info/METADATA
SSG_API_test-0.0.3.dist-info/WHEEL
SSG_API_test-0.0.3.dist-info/top_level.txt
SSG_API_test-0.0.3.dist-info/RECORD
